zermelo_for_python/__init__.py
zermelo_for_python/schedule.py
zermelo_for_python/scheduleaction.py
zermelo_for_python/scheduleitem.py
zermelo_for_python-2024.11.13.12.34.5.dist-info/METADATA
zermelo_for_python-2024.11.13.12.34.5.dist-info/WHEEL
zermelo_for_python-2024.11.13.12.34.5.dist-info/top_level.txt
zermelo_for_python-2024.11.13.12.34.5.dist-info/RECORD
