Metadata-Version: 2.1
Name: zermelo-for-python
Version: 2024.11.13.12.34.5
Summary: zermelo api for python
Home-page: https://gitlab.com/btpv/zermelo_for_python
Author: b.vill
Author-email: villeriusborro@gmail.com
Keywords: zermelo,api
Classifier: Programming Language :: Python :: 3
Classifier: License :: OSI Approved :: MIT License
Classifier: Operating System :: OS Independent
Requires-Python: >=3.0
Requires-Dist: datetime
Requires-Dist: requests
